mumath/__init__.py
mumath/config.py
mumath/core.py
mumath/glyph.py
mumath/grammar.py
mumath/lex.py
mumath/markdown.py
mumath/server.py
mumath/util.py
mumath/context/__init__.py
mumath/context/base.py
mumath/context/chemistry.py
mumath/context/physics.py
mumath/context/statistics.py
mumath/context/tokens.py
mumath/data/index.html
mumath/node/__init__.py
mumath/node/mathml.py
mumath/node/util.py
mumath/node/writer.py
mumath-1.3.8.dist-info/licenses/LICENSE
mumath-1.3.8.dist-info/METADATA
mumath-1.3.8.dist-info/WHEEL
mumath-1.3.8.dist-info/entry_points.txt
mumath-1.3.8.dist-info/top_level.txt
mumath-1.3.8.dist-info/RECORD
